funicorn/__init__.py
funicorn/exceptions.py
funicorn/funicorn.py
funicorn/http_api.py
funicorn/logger.py
funicorn/mqueue.py
funicorn/stat.py
funicorn/table.py
funicorn/utils.py
funicorn/cli/__init__.py
funicorn/client/__init__.py
funicorn/rpc/FunicornService.py
funicorn/rpc/__init__.py
funicorn/rpc/constants.py
funicorn/rpc/rpc_api.py
funicorn/rpc/ttypes.py
funicorn/rpc/thrift_server/TModelPool.py
funicorn/rpc/thrift_server/__init__.py
funicorn-1.0.6.dist-info/METADATA
funicorn-1.0.6.dist-info/WHEEL
funicorn-1.0.6.dist-info/entry_points.txt
funicorn-1.0.6.dist-info/top_level.txt
funicorn-1.0.6.dist-info/RECORD
